qwantz_metadata/__init__.py
qwantz_metadata/chars_by_year.py
qwantz_metadata/combine_metadata.py
qwantz_metadata/hapax_legomena.py
qwantz_metadata/parse_qwantz_html.py
qwantz_metadata/utils.py
qwantz_metadata/data/extra_metadata.json
qwantz_metadata/data/guest_comics.json
qwantz_metadata/data/special_comics.json
qwantz_metadata-2025.9.0.dist-info/licenses/LICENSE
qwantz_metadata-2025.9.0.dist-info/METADATA
qwantz_metadata-2025.9.0.dist-info/WHEEL
qwantz_metadata-2025.9.0.dist-info/entry_points.txt
qwantz_metadata-2025.9.0.dist-info/top_level.txt
qwantz_metadata-2025.9.0.dist-info/RECORD
