Metadata-Version: 2.4
Name: qwantz_metadata
Version: 2025.9.0
Summary: Prepare metadata document for Dinosaur Comics
Author-email: Jan Szejko <jan.szejko@gmail.com>
Project-URL: homepage, https://github.com/janek37/qwantz_metadata
Classifier: Development Status :: 3 - Alpha
Classifier: Programming Language :: Python :: 3.10
Classifier: Environment :: Console
Classifier: Intended Audience :: End Users/Desktop
Classifier: License :: OSI Approved :: MIT License
Classifier: Natural Language :: English
Classifier: Operating System :: OS Independent
Classifier: Topic :: Text Processing :: Markup :: HTML
Classifier: Topic :: Text Processing :: General
Classifier: Typing :: Typed
Requires-Python: >=3.10
License-File: LICENSE
Requires-Dist: beautifulsoup4
Requires-Dist: python-dateutil
Requires-Dist: typer
Provides-Extra: dev
Requires-Dist: pytest; extra == "dev"
Dynamic: license-file
